{
  "en": {
    "plugin.name": "FreshBooks Invoices",
    "plugin.summary": "Create Invoices from your recorded hours with the FreshBooks plugin. The integration with time tracking in Tyme allows you to automatically transfer your hours without any friction.",
    "locale.identifier": "en-US",
    "button.auth": "Connect with FreshBooks",
    "button.logout": "Disconnect from FreshBooks",
    "input.daterange": "Date Range",
    "input.prefixProject": "Prefix with project title",
    "input.notes": "",
    "input.note.times": "",
    "input.cluster": "",
    "input.cluster.none": "",
    "input.cluster.dayTask": "",
    "input.cluster.dayTaskNoSub": "",
    "input.client": "",
    "input.tax": "",
    "input.tax.empty": "",
    "input.unbilled": "",
    "input.billed": "",
    "input.nonbillable": ""
  },
  "de": {
    "plugin.name": "FreshBooks Rechnungen",
    "plugin.summary": "Erstelle Rechnungen aus deinen erfassten Stunden mit dem FreshBooks-Plugin. Durch die Integration mit der Zeiterfassung in Tyme kannst du deine Stunden automatisch und reibungslos übertragen.",
    "locale.identifier": "de-DE",
    "button.auth": "Mit FreshBooks verbinden",
    "button.logout": "Verbindung mit FreshBooks trennen",
    "input.daterange": "Zeitraum",
    "input.prefixProject": "Präfix Projekt-Titel",
    "input.notes": "",
    "input.note.times": "",
    "input.cluster": "",
    "input.cluster.none": "",
    "input.cluster.dayTask": "",
    "input.cluster.dayTaskNoSub": "",
    "input.client": "",
    "input.tax": "",
    "input.tax.empty": "",
    "input.unbilled": "",
    "input.billed": "",
    "input.nonbillable": ""
  }
}
